{
    "DNDConfig": null,
    "__parentReadjusting__": false,
    "_height_": {
        "type": "string",
        "value": "90%"
    },
    "_left_": {
        "type": "string",
        "value": "0dp"
    },
    "_margin_": [
        0,
        0,
        0,
        0
    ],
    "_orientation_": 6,
    "_padding_": [
        0,
        0,
        0,
        0
    ],
    "_percent_": true,
    "_skin_": "s7402769af5340818f6ecb76bbb6e1eb",
    "_top_": {
        "type": "string",
        "value": "0dp"
    },
    "_width_": {
        "type": "string",
        "value": "90%"
    },
    "allboxes": [],
    "autogrowmode": 0,
    "canUpdateUI": true,
    "centerx": {
        "type": "string",
        "value": "50%"
    },
    "children": [
        "registrationPageAccountTitle",
        "regEmailAddressTitle",
        "regEmailAddressInput",
        "regPasswordTitle",
        "regPasswordInput",
        "Label00faa1b8d9e104f",
        "regReenterPasswordTitle",
        "regReenterPasswordInput"
    ],
    "clipbounds": true,
    "containerweight": 100,
    "enablescrolling": true,
    "id": "regAccountInfoContainer",
    "info": null,
    "isvisible": true,
    "kuid": "bbb35799ccd74ca798b628ce9c3f6594",
    "layouttype": 4,
    "name": "kony.ui.FlexContainer",
    "parent": "registrationAccountPage",
    "pf": "registrationAccountPage",
    "snapgridsize": 10,
    "snaptogrid": true,
    "wType": "FlexContainer",
    "widgetalignment": 1,
    "zindex": 1
}