{
    "AS_FlexContainer_cae27a7e255946aba75457f13ce68dd9": {
        "id": "AS_FlexContainer_cae27a7e255946aba75457f13ce68dd9",
        "type": "ACTION_SEQUENCE",
        "params": [{
            "datatype": "collection",
            "name": "eventobject"
        }, {
            "datatype": "string",
            "name": "x"
        }, {
            "datatype": "string",
            "name": "y"
        }],
        "contextObj": {
            "name": "FBox0baca4c5b3ff848",
            "type": "templates",
            "platform": "",
            "KUID": "8a8756880f7e49b0bfced9c9198e839d"
        },
        "language": "js",
        "actions": []
    }
}